mgp2pdf.py
mgp2pdf-0.11.0.dist-info/LICENSE
mgp2pdf-0.11.0.dist-info/METADATA
mgp2pdf-0.11.0.dist-info/WHEEL
mgp2pdf-0.11.0.dist-info/entry_points.txt
mgp2pdf-0.11.0.dist-info/top_level.txt
mgp2pdf-0.11.0.dist-info/RECORD
